{
  "project_info": {
    "project_number": "240717446524",
    "firebase_url": "https://chat-ce4d6.firebaseio.com",
    "project_id": "chat-ce4d6",
    "storage_bucket": "chat-ce4d6.appspot.com"
  },
  "client": [
    {
      "client_info": {
        "mobilesdk_app_id": "1:240717446524:android:ae00846ba691f0970338f9",
        "android_client_info": {
          "package_name": "com.softtech.android_structure"
        }
      },
      "oauth_client": [
        {
          "client_id": "240717446524-kqlsu4k3gt7c3tnlqtehbgclj9sbrbvi.apps.googleusercontent.com",
          "client_type": 1,
          "android_info": {
            "package_name": "com.softtech.android_structure",
            "certificate_hash": "0d9b7ce3c33e436d12f1d9c941f0e6026a335c9a"
          }
        },
        {
          "client_id": "240717446524-7mpu9u8p1r5vk1i6gtkdf9dp5s2v8kjd.apps.googleusercontent.com",
          "client_type": 3
        }
      ],
      "api_key": [
        {
          "current_key": "AIzaSyB6B0cSZVCfarXAEsNoelX_VyQGmLVjd74"
        }
      ],
      "services": {
        "appinvite_service": {
          "other_platform_oauth_client": [
            {
              "client_id": "240717446524-7mpu9u8p1r5vk1i6gtkdf9dp5s2v8kjd.apps.googleusercontent.com",
              "client_type": 3
            }
          ]
        }
      }
    }
  ],
  "configuration_version": "1"
}